{
  "test_vectors": [
    {
      "name": "batch_referral_reward_success",
      "description": "",
      "pre_state": {
        "network_chain_id": 3,
        "global_state": {
          "total_supply": 0,
          "total_burned": 0,
          "total_energy": 0,
          "block_height": 0,
          "timestamp": 0
        },
        "accounts": [
          {
            "address": "f05bc1df2831717c2992d85b57e0cf3d123fd6c254257de5f784be369747b249",
            "balance": 1000000,
            "nonce": 5,
            "frozen": 0,
            "energy": 0,
            "flags": 0,
            "data": ""
          },
          {
            "address": "c29d170ab8a5b42a3520878501a87a27f9b5653fca8b0c59fc2786cf26e37824",
            "balance": 0,
            "nonce": 0,
            "frozen": 0,
            "energy": 0,
            "flags": 0,
            "data": ""
          },
          {
            "address": "7ea555bf91bfb985561a91afcd669a79c0cc115ce03baf687cb8dd7e1e996e7b",
            "balance": 0,
            "nonce": 0,
            "frozen": 0,
            "energy": 0,
            "flags": 0,
            "data": ""
          }
        ],
        "referrals": [
          {
            "user": "c29d170ab8a5b42a3520878501a87a27f9b5653fca8b0c59fc2786cf26e37824",
            "referrer": "7ea555bf91bfb985561a91afcd669a79c0cc115ce03baf687cb8dd7e1e996e7b"
          }
        ]
      },
      "runnable": false,
      "input": {
        "kind": "tx",
        "wire_hex": "",
        "tx": {
          "version": 1,
          "chain_id": 3,
          "source": "f05bc1df2831717c2992d85b57e0cf3d123fd6c254257de5f784be369747b249",
          "tx_type": "batch_referral_reward",
          "payload": {
            "total_amount": 100000,
            "levels": 1,
            "ratios": [
              5000
            ],
            "from_user": "c29d170ab8a5b42a3520878501a87a27f9b5653fca8b0c59fc2786cf26e37824"
          },
          "fee": 100000,
          "fee_type": 0,
          "nonce": 5,
          "reference_hash": "0000000000000000000000000000000000000000000000000000000000000000",
          "reference_topoheight": 0,
          "signature": "00000000000000000000000000000000000000000000000000000000000000000000000000000000000000000000000000000000000000000000000000000000",
          "wire_hex": ""
        }
      },
      "expected": {
        "success": true,
        "error_code": 0,
        "state_digest": "9e6d228d5ed50e109d74b71977d08f687a8a3638873abfb5f4304cbf6ea3c336",
        "post_state": {
          "network_chain_id": 3,
          "global_state": {
            "total_supply": 0,
            "total_burned": 0,
            "total_energy": 0,
            "block_height": 0,
            "timestamp": 0
          },
          "accounts": [
            {
              "address": "f05bc1df2831717c2992d85b57e0cf3d123fd6c254257de5f784be369747b249",
              "balance": 800000,
              "nonce": 6,
              "frozen": 0,
              "energy": 0,
              "flags": 0,
              "data": ""
            },
            {
              "address": "c29d170ab8a5b42a3520878501a87a27f9b5653fca8b0c59fc2786cf26e37824",
              "balance": 0,
              "nonce": 0,
              "frozen": 0,
              "energy": 0,
              "flags": 0,
              "data": ""
            },
            {
              "address": "7ea555bf91bfb985561a91afcd669a79c0cc115ce03baf687cb8dd7e1e996e7b",
              "balance": 50000,
              "nonce": 0,
              "frozen": 0,
              "energy": 0,
              "flags": 0,
              "data": ""
            }
          ],
          "referrals": [
            {
              "user": "c29d170ab8a5b42a3520878501a87a27f9b5653fca8b0c59fc2786cf26e37824",
              "referrer": "7ea555bf91bfb985561a91afcd669a79c0cc115ce03baf687cb8dd7e1e996e7b"
            }
          ]
        }
      }
    },
    {
      "name": "batch_referral_reward_zero_amount",
      "description": "",
      "pre_state": {
        "network_chain_id": 3,
        "global_state": {
          "total_supply": 0,
          "total_burned": 0,
          "total_energy": 0,
          "block_height": 0,
          "timestamp": 0
        },
        "accounts": [
          {
            "address": "f05bc1df2831717c2992d85b57e0cf3d123fd6c254257de5f784be369747b249",
            "balance": 1000000,
            "nonce": 5,
            "frozen": 0,
            "energy": 0,
            "flags": 0,
            "data": ""
          },
          {
            "address": "c29d170ab8a5b42a3520878501a87a27f9b5653fca8b0c59fc2786cf26e37824",
            "balance": 0,
            "nonce": 0,
            "frozen": 0,
            "energy": 0,
            "flags": 0,
            "data": ""
          }
        ]
      },
      "runnable": false,
      "input": {
        "kind": "tx",
        "wire_hex": "",
        "tx": {
          "version": 1,
          "chain_id": 3,
          "source": "f05bc1df2831717c2992d85b57e0cf3d123fd6c254257de5f784be369747b249",
          "tx_type": "batch_referral_reward",
          "payload": {
            "total_amount": 0,
            "levels": 1,
            "ratios": [
              5000
            ],
            "from_user": "c29d170ab8a5b42a3520878501a87a27f9b5653fca8b0c59fc2786cf26e37824"
          },
          "fee": 100000,
          "fee_type": 0,
          "nonce": 5,
          "reference_hash": "0000000000000000000000000000000000000000000000000000000000000000",
          "reference_topoheight": 0,
          "signature": "00000000000000000000000000000000000000000000000000000000000000000000000000000000000000000000000000000000000000000000000000000000",
          "wire_hex": ""
        }
      },
      "expected": {
        "success": false,
        "error_code": 261,
        "state_digest": "7c75aa8cc3b02395ff3b4475ce54dd6fd1157fbeafa9bb55142b81a467d88880",
        "post_state": {
          "network_chain_id": 3,
          "global_state": {
            "total_supply": 0,
            "total_burned": 0,
            "total_energy": 0,
            "block_height": 0,
            "timestamp": 0
          },
          "accounts": [
            {
              "address": "f05bc1df2831717c2992d85b57e0cf3d123fd6c254257de5f784be369747b249",
              "balance": 1000000,
              "nonce": 5,
              "frozen": 0,
              "energy": 0,
              "flags": 0,
              "data": ""
            },
            {
              "address": "c29d170ab8a5b42a3520878501a87a27f9b5653fca8b0c59fc2786cf26e37824",
              "balance": 0,
              "nonce": 0,
              "frozen": 0,
              "energy": 0,
              "flags": 0,
              "data": ""
            }
          ]
        }
      }
    },
    {
      "name": "batch_referral_reward_ratio_exceeds_max",
      "description": "",
      "pre_state": {
        "network_chain_id": 3,
        "global_state": {
          "total_supply": 0,
          "total_burned": 0,
          "total_energy": 0,
          "block_height": 0,
          "timestamp": 0
        },
        "accounts": [
          {
            "address": "f05bc1df2831717c2992d85b57e0cf3d123fd6c254257de5f784be369747b249",
            "balance": 1000000,
            "nonce": 5,
            "frozen": 0,
            "energy": 0,
            "flags": 0,
            "data": ""
          },
          {
            "address": "c29d170ab8a5b42a3520878501a87a27f9b5653fca8b0c59fc2786cf26e37824",
            "balance": 0,
            "nonce": 0,
            "frozen": 0,
            "energy": 0,
            "flags": 0,
            "data": ""
          }
        ]
      },
      "runnable": false,
      "input": {
        "kind": "tx",
        "wire_hex": "",
        "tx": {
          "version": 1,
          "chain_id": 3,
          "source": "f05bc1df2831717c2992d85b57e0cf3d123fd6c254257de5f784be369747b249",
          "tx_type": "batch_referral_reward",
          "payload": {
            "total_amount": 100000,
            "levels": 2,
            "ratios": [
              6000,
              5000
            ],
            "from_user": "c29d170ab8a5b42a3520878501a87a27f9b5653fca8b0c59fc2786cf26e37824"
          },
          "fee": 100000,
          "fee_type": 0,
          "nonce": 5,
          "reference_hash": "0000000000000000000000000000000000000000000000000000000000000000",
          "reference_topoheight": 0,
          "signature": "00000000000000000000000000000000000000000000000000000000000000000000000000000000000000000000000000000000000000000000000000000000",
          "wire_hex": ""
        }
      },
      "expected": {
        "success": false,
        "error_code": 263,
        "state_digest": "7c75aa8cc3b02395ff3b4475ce54dd6fd1157fbeafa9bb55142b81a467d88880",
        "post_state": {
          "network_chain_id": 3,
          "global_state": {
            "total_supply": 0,
            "total_burned": 0,
            "total_energy": 0,
            "block_height": 0,
            "timestamp": 0
          },
          "accounts": [
            {
              "address": "f05bc1df2831717c2992d85b57e0cf3d123fd6c254257de5f784be369747b249",
              "balance": 1000000,
              "nonce": 5,
              "frozen": 0,
              "energy": 0,
              "flags": 0,
              "data": ""
            },
            {
              "address": "c29d170ab8a5b42a3520878501a87a27f9b5653fca8b0c59fc2786cf26e37824",
              "balance": 0,
              "nonce": 0,
              "frozen": 0,
              "energy": 0,
              "flags": 0,
              "data": ""
            }
          ]
        }
      }
    },
    {
      "name": "batch_referral_reward_levels_mismatch",
      "description": "",
      "pre_state": {
        "network_chain_id": 3,
        "global_state": {
          "total_supply": 0,
          "total_burned": 0,
          "total_energy": 0,
          "block_height": 0,
          "timestamp": 0
        },
        "accounts": [
          {
            "address": "f05bc1df2831717c2992d85b57e0cf3d123fd6c254257de5f784be369747b249",
            "balance": 1000000,
            "nonce": 5,
            "frozen": 0,
            "energy": 0,
            "flags": 0,
            "data": ""
          },
          {
            "address": "c29d170ab8a5b42a3520878501a87a27f9b5653fca8b0c59fc2786cf26e37824",
            "balance": 0,
            "nonce": 0,
            "frozen": 0,
            "energy": 0,
            "flags": 0,
            "data": ""
          }
        ]
      },
      "runnable": false,
      "input": {
        "kind": "tx",
        "wire_hex": "",
        "tx": {
          "version": 1,
          "chain_id": 3,
          "source": "f05bc1df2831717c2992d85b57e0cf3d123fd6c254257de5f784be369747b249",
          "tx_type": "batch_referral_reward",
          "payload": {
            "total_amount": 100000,
            "levels": 3,
            "ratios": [
              5000,
              3000
            ],
            "from_user": "c29d170ab8a5b42a3520878501a87a27f9b5653fca8b0c59fc2786cf26e37824"
          },
          "fee": 100000,
          "fee_type": 0,
          "nonce": 5,
          "reference_hash": "0000000000000000000000000000000000000000000000000000000000000000",
          "reference_topoheight": 0,
          "signature": "00000000000000000000000000000000000000000000000000000000000000000000000000000000000000000000000000000000000000000000000000000000",
          "wire_hex": ""
        }
      },
      "expected": {
        "success": false,
        "error_code": 263,
        "state_digest": "7c75aa8cc3b02395ff3b4475ce54dd6fd1157fbeafa9bb55142b81a467d88880",
        "post_state": {
          "network_chain_id": 3,
          "global_state": {
            "total_supply": 0,
            "total_burned": 0,
            "total_energy": 0,
            "block_height": 0,
            "timestamp": 0
          },
          "accounts": [
            {
              "address": "f05bc1df2831717c2992d85b57e0cf3d123fd6c254257de5f784be369747b249",
              "balance": 1000000,
              "nonce": 5,
              "frozen": 0,
              "energy": 0,
              "flags": 0,
              "data": ""
            },
            {
              "address": "c29d170ab8a5b42a3520878501a87a27f9b5653fca8b0c59fc2786cf26e37824",
              "balance": 0,
              "nonce": 0,
              "frozen": 0,
              "energy": 0,
              "flags": 0,
              "data": ""
            }
          ]
        }
      }
    },
    {
      "name": "batch_referral_reward_max_ratio",
      "description": "",
      "pre_state": {
        "network_chain_id": 3,
        "global_state": {
          "total_supply": 0,
          "total_burned": 0,
          "total_energy": 0,
          "block_height": 0,
          "timestamp": 0
        },
        "accounts": [
          {
            "address": "f05bc1df2831717c2992d85b57e0cf3d123fd6c254257de5f784be369747b249",
            "balance": 1000000,
            "nonce": 5,
            "frozen": 0,
            "energy": 0,
            "flags": 0,
            "data": ""
          },
          {
            "address": "c29d170ab8a5b42a3520878501a87a27f9b5653fca8b0c59fc2786cf26e37824",
            "balance": 0,
            "nonce": 0,
            "frozen": 0,
            "energy": 0,
            "flags": 0,
            "data": ""
          },
          {
            "address": "7ea555bf91bfb985561a91afcd669a79c0cc115ce03baf687cb8dd7e1e996e7b",
            "balance": 0,
            "nonce": 0,
            "frozen": 0,
            "energy": 0,
            "flags": 0,
            "data": ""
          }
        ],
        "referrals": [
          {
            "user": "c29d170ab8a5b42a3520878501a87a27f9b5653fca8b0c59fc2786cf26e37824",
            "referrer": "7ea555bf91bfb985561a91afcd669a79c0cc115ce03baf687cb8dd7e1e996e7b"
          }
        ]
      },
      "runnable": false,
      "input": {
        "kind": "tx",
        "wire_hex": "",
        "tx": {
          "version": 1,
          "chain_id": 3,
          "source": "f05bc1df2831717c2992d85b57e0cf3d123fd6c254257de5f784be369747b249",
          "tx_type": "batch_referral_reward",
          "payload": {
            "total_amount": 100000,
            "levels": 1,
            "ratios": [
              10000
            ],
            "from_user": "c29d170ab8a5b42a3520878501a87a27f9b5653fca8b0c59fc2786cf26e37824"
          },
          "fee": 100000,
          "fee_type": 0,
          "nonce": 5,
          "reference_hash": "0000000000000000000000000000000000000000000000000000000000000000",
          "reference_topoheight": 0,
          "signature": "00000000000000000000000000000000000000000000000000000000000000000000000000000000000000000000000000000000000000000000000000000000",
          "wire_hex": ""
        }
      },
      "expected": {
        "success": true,
        "error_code": 0,
        "state_digest": "a39842b5b4918a4af5bf75dcbf46608a736ce9d9dcc65ab1549e73b2f5a07e1a",
        "post_state": {
          "network_chain_id": 3,
          "global_state": {
            "total_supply": 0,
            "total_burned": 0,
            "total_energy": 0,
            "block_height": 0,
            "timestamp": 0
          },
          "accounts": [
            {
              "address": "f05bc1df2831717c2992d85b57e0cf3d123fd6c254257de5f784be369747b249",
              "balance": 800000,
              "nonce": 6,
              "frozen": 0,
              "energy": 0,
              "flags": 0,
              "data": ""
            },
            {
              "address": "c29d170ab8a5b42a3520878501a87a27f9b5653fca8b0c59fc2786cf26e37824",
              "balance": 0,
              "nonce": 0,
              "frozen": 0,
              "energy": 0,
              "flags": 0,
              "data": ""
            },
            {
              "address": "7ea555bf91bfb985561a91afcd669a79c0cc115ce03baf687cb8dd7e1e996e7b",
              "balance": 100000,
              "nonce": 0,
              "frozen": 0,
              "energy": 0,
              "flags": 0,
              "data": ""
            }
          ],
          "referrals": [
            {
              "user": "c29d170ab8a5b42a3520878501a87a27f9b5653fca8b0c59fc2786cf26e37824",
              "referrer": "7ea555bf91bfb985561a91afcd669a79c0cc115ce03baf687cb8dd7e1e996e7b"
            }
          ]
        }
      }
    }
  ]
}